scenebuilder/__init__.py
scenebuilder/actions_stack.py
scenebuilder/entities.py
scenebuilder/main.py
scenebuilder/mixins.py
scenebuilder/observer_utils.py
scenebuilder/patch_manager.py
scenebuilder/patches.py
scenebuilder/scenebuilder.py
scenebuilder/ui_components.py
scenebuilder/utils.py
scenebuilder-0.3.1.dist-info/METADATA
scenebuilder-0.3.1.dist-info/WHEEL
scenebuilder-0.3.1.dist-info/entry_points.txt
scenebuilder-0.3.1.dist-info/RECORD
