Metadata-Version: 2.1
Name: scenebuilder
Version: 0.3.1
Summary: A simple GUI to create 2D scenes with obstacles and drone paths for multi-agent path planning algorithms
Author: Adrian del Ser
Author-email: adrian.delser@gmail.com
Requires-Python: >=3.10
Classifier: Programming Language :: Python :: 3
Classifier: Programming Language :: Python :: 3.10
Classifier: Programming Language :: Python :: 3.11
Classifier: Programming Language :: Python :: 3.12
Requires-Dist: matplotlib (>=3.8.0,<4.0.0)
Requires-Dist: numpy (>=1.26.1,<2.0.0)
